vixio/__init__.py
vixio/cli.py
vixio/config/__init__.py
vixio/config/loader.py
vixio/config/schema.py
vixio/core/__init__.py
vixio/core/chunk.py
vixio/core/control_bus.py
vixio/core/dag.py
vixio/core/dag_events.py
vixio/core/dag_monitor.py
vixio/core/middleware.py
vixio/core/output_controller.py
vixio/core/protocol.py
vixio/core/session.py
vixio/core/session_context.py
vixio/core/station.py
vixio/core/transport.py
vixio/core/tools/__init__.py
vixio/core/tools/converter.py
vixio/core/tools/device.py
vixio/core/tools/local.py
vixio/core/tools/types.py
vixio/providers/__init__.py
vixio/providers/agent.py
vixio/providers/asr.py
vixio/providers/base.py
vixio/providers/factory.py
vixio/providers/realtime.py
vixio/providers/registry.py
vixio/providers/tts.py
vixio/providers/vad.py
vixio/providers/vision.py
vixio/providers/doubao/__init__.py
vixio/providers/doubao/doubao_realtime.py
vixio/providers/doubao/doubao_tts_bidirectional.py
vixio/providers/edge_tts/__init__.py
vixio/providers/edge_tts/provider.py
vixio/providers/kokoro_cn_tts_local/__init__.py
vixio/providers/kokoro_cn_tts_local/client.py
vixio/providers/kokoro_cn_tts_local/grpc_provider.py
vixio/providers/kokoro_cn_tts_local/local_provider.py
vixio/providers/kokoro_cn_tts_local/tts_pb2.py
vixio/providers/kokoro_cn_tts_local/tts_pb2_grpc.py
vixio/providers/openai_agent/__init__.py
vixio/providers/openai_agent/dump_promt.py
vixio/providers/openai_agent/provider.py
vixio/providers/openai_agent/tools.py
vixio/providers/qwen/__init__.py
vixio/providers/qwen/qwen3_asr_flash_realtime.py
vixio/providers/qwen/qwen3_tts_flash_realtime.py
vixio/providers/qwen/qwen_omni_realtime.py
vixio/providers/sentence_aggregator/__init__.py
vixio/providers/sentence_aggregator/base.py
vixio/providers/sentence_aggregator/simple_provider_cn.py
vixio/providers/sherpa_onnx_local/__init__.py
vixio/providers/sherpa_onnx_local/asr_pb2.py
vixio/providers/sherpa_onnx_local/asr_pb2_grpc.py
vixio/providers/sherpa_onnx_local/client.py
vixio-0.1.5.dist-info/licenses/LICENSE
vixio-0.1.5.dist-info/METADATA
vixio-0.1.5.dist-info/WHEEL
vixio-0.1.5.dist-info/entry_points.txt
vixio-0.1.5.dist-info/top_level.txt
vixio-0.1.5.dist-info/RECORD
