Metadata-Version: 2.4
Name: vixio
Version: 0.1.5
Summary: Voice-Powered Agent Framework
Author: Weyne Chen
License-Expression: MIT
Project-URL: Homepage, https://github.com/weynechen/vixio
Project-URL: Repository, https://github.com/weynechen/vixio
Project-URL: Issues, https://github.com/weynechen/vixio/issues
Keywords: voice,agent,ai,speech,framework
Classifier: Development Status :: 3 - Alpha
Classifier: Intended Audience :: Developers
Classifier: Programming Language :: Python :: 3
Classifier: Programming Language :: Python :: 3.12
Classifier: Topic :: Software Development :: Libraries :: Python Modules
Classifier: Topic :: Scientific/Engineering :: Artificial Intelligence
Requires-Python: >=3.12
License-File: LICENSE
Requires-Dist: pydantic>=2.5.0
Requires-Dist: pydantic-settings>=2.1.0
Requires-Dist: ruamel.yaml>=0.18.16
Requires-Dist: loguru>=0.7.3
Provides-Extra: xiaozhi
Requires-Dist: fastapi>=0.110.0; extra == "xiaozhi"
Requires-Dist: uvicorn[standard]>=0.27.0; extra == "xiaozhi"
Requires-Dist: websockets<15.0,>=14.0; extra == "xiaozhi"
Requires-Dist: opuslib_next>=1.1.5; extra == "xiaozhi"
Requires-Dist: PyJWT>=2.10.0; extra == "xiaozhi"
Requires-Dist: aiohttp>=3.13.0; extra == "xiaozhi"
Requires-Dist: aiohttp-cors>=0.8.0; extra == "xiaozhi"
Requires-Dist: numpy<2.0.0,>=1.26.0; extra == "xiaozhi"
Provides-Extra: silero-vad-grpc
Requires-Dist: grpcio>=1.76.0; extra == "silero-vad-grpc"
Requires-Dist: grpcio-tools>=1.76.0; extra == "silero-vad-grpc"
Provides-Extra: sherpa-onnx-asr-grpc
Requires-Dist: grpcio>=1.76.0; extra == "sherpa-onnx-asr-grpc"
Requires-Dist: grpcio-tools>=1.76.0; extra == "sherpa-onnx-asr-grpc"
Requires-Dist: numpy<2.0.0,>=1.26.0; extra == "sherpa-onnx-asr-grpc"
Provides-Extra: kokoro-cn-tts-grpc
Requires-Dist: grpcio>=1.76.0; extra == "kokoro-cn-tts-grpc"
Requires-Dist: grpcio-tools>=1.76.0; extra == "kokoro-cn-tts-grpc"
Requires-Dist: numpy<2.0.0,>=1.26.0; extra == "kokoro-cn-tts-grpc"
Provides-Extra: silero-vad-local
Requires-Dist: onnxruntime-gpu>=1.16.0; extra == "silero-vad-local"
Requires-Dist: numpy>=1.24.0; extra == "silero-vad-local"
Requires-Dist: silero-vad>=5.0; extra == "silero-vad-local"
Provides-Extra: sherpa-onnx-asr-local
Requires-Dist: onnxruntime-gpu>=1.16.0; extra == "sherpa-onnx-asr-local"
Requires-Dist: numpy>=1.24.0; extra == "sherpa-onnx-asr-local"
Requires-Dist: sherpa-onnx>=1.12.15; extra == "sherpa-onnx-asr-local"
Requires-Dist: huggingface_hub>=0.20.0; extra == "sherpa-onnx-asr-local"
Provides-Extra: kokoro-cn-tts-local
Requires-Dist: torch>=2.0.0; extra == "kokoro-cn-tts-local"
Requires-Dist: numpy>=1.24.0; extra == "kokoro-cn-tts-local"
Requires-Dist: kokoro>=0.8.1; extra == "kokoro-cn-tts-local"
Requires-Dist: misaki[zh]>=0.8.1; extra == "kokoro-cn-tts-local"
Provides-Extra: openai-agent
Requires-Dist: openai-agents[litellm]>=0.4.2; extra == "openai-agent"
Requires-Dist: openai>=2.7.0; extra == "openai-agent"
Requires-Dist: httpx>=0.28.0; extra == "openai-agent"
Provides-Extra: edge-tts
Requires-Dist: edge-tts>=7.2.3; extra == "edge-tts"
Requires-Dist: pydub>=0.25.0; extra == "edge-tts"
Provides-Extra: qwen
Requires-Dist: dashscope>=1.25.3; extra == "qwen"
Provides-Extra: doubao
Requires-Dist: websockets>=14.0; extra == "doubao"
Provides-Extra: dev-local-cn
Requires-Dist: vixio[kokoro-cn-tts-local,openai-agent,sherpa-onnx-asr-local,silero-vad-local,xiaozhi]; extra == "dev-local-cn"
Provides-Extra: dev-grpc
Requires-Dist: vixio[kokoro-cn-tts-grpc,openai-agent,sherpa-onnx-asr-grpc,silero-vad-grpc,xiaozhi]; extra == "dev-grpc"
Provides-Extra: dev-qwen
Requires-Dist: vixio[openai-agent,qwen,silero-vad-local,xiaozhi]; extra == "dev-qwen"
Provides-Extra: dev-qwen-streaming
Requires-Dist: vixio[openai-agent,qwen,xiaozhi]; extra == "dev-qwen-streaming"
Provides-Extra: dev-doubao
Requires-Dist: vixio[doubao,openai-agent,xiaozhi]; extra == "dev-doubao"
Provides-Extra: quickstart
Requires-Dist: vixio[openai-agent,qwen,silero-vad-local,xiaozhi]; extra == "quickstart"
Provides-Extra: test
Requires-Dist: pytest>=7.4.0; extra == "test"
Requires-Dist: pytest-asyncio>=0.21.0; extra == "test"
Requires-Dist: pytest-cov>=4.1.0; extra == "test"
Requires-Dist: black>=23.7.0; extra == "test"
Requires-Dist: isort>=5.12.0; extra == "test"
Requires-Dist: mypy>=1.5.0; extra == "test"
Requires-Dist: ruff>=0.0.287; extra == "test"
Requires-Dist: pydub; extra == "test"
Requires-Dist: psutil>=7.0.0; extra == "test"
Dynamic: license-file
